[
  {
    "id": "12971610433",
    "type": "PushEvent",
    "actor": {
      "id": 44237969,
      "login": "Samuel-Martineau",
      "display_login": "Samuel-Martineau",
      "gravatar_id": "",
      "url": "https://api.github.com/users/Samuel-Martineau",
      "avatar_url": "https://avatars.githubusercontent.com/u/44237969?"
    },
    "repo": {
      "id": 280742722,
      "name": "Samuel-Martineau/Potions-HUD-Fabric",
      "url": "https://api.github.com/repos/Samuel-Martineau/Potions-HUD-Fabric"
    },
    "payload": {
      "push_id": 5408191444,
      "size": 1,
      "distinct_size": 1,
      "ref": "refs/heads/master",
      "head": "c18252c15ea662a68e72ece3c6ee669395ef75f2",
      "before": "c848859fde8dbfd5da4c67c68232fb9063c3f83c",
      "commits": [
        {
          "sha": "c18252c15ea662a68e72ece3c6ee669395ef75f2",
          "author": {
            "email": "samumartineau@gmail.com",
            "name": "Samuel-Martineau"
          },
          "message": "Update README.md",
          "distinct": true,
          "url": "https://api.github.com/repos/Samuel-Martineau/Potions-HUD-Fabric/commits/c18252c15ea662a68e72ece3c6ee669395ef75f2"
        }
      ]
    },
    "public": true,
    "created_at": "2020-07-21T11:13:19Z"
  },
  {
    "id": "12966588891",
    "type": "WatchEvent",
    "actor": {
      "id": 44237969,
      "login": "Samuel-Martineau",
      "display_login": "Samuel-Martineau",
      "gravatar_id": "",
      "url": "https://api.github.com/users/Samuel-Martineau",
      "avatar_url": "https://avatars.githubusercontent.com/u/44237969?"
    },
    "repo": {
      "id": 280742722,
      "name": "Samuel-Martineau/Potions-HUD-Fabric",
      "url": "https://api.github.com/repos/Samuel-Martineau/Potions-HUD-Fabric"
    },
    "payload": {
      "action": "started"
    },
    "public": true,
    "created_at": "2020-07-21T01:03:12Z"
  },
  {
    "id": "12964524394",
    "type": "PushEvent",
    "actor": {
      "id": 44237969,
      "login": "Samuel-Martineau",
      "display_login": "Samuel-Martineau",
      "gravatar_id": "",
      "url": "https://api.github.com/users/Samuel-Martineau",
      "avatar_url": "https://avatars.githubusercontent.com/u/44237969?"
    },
    "repo": {
      "id": 279429394,
      "name": "Samuel-Martineau/Smartineau.me",
      "url": "https://api.github.com/repos/Samuel-Martineau/Smartineau.me"
    },
    "payload": {
      "push_id": 5404590841,
      "size": 2,
      "distinct_size": 2,
      "ref": "refs/heads/master",
      "head": "061cb7b41f0f98c02f77af438b0aa4e1ed73d547",
      "before": "3a2666c7257e247611be794245446664d06c6875",
      "commits": [
        {
          "sha": "b59b7357f08b85a29c9a5c1a7c7abfd7abe66fa5",
          "author": {
            "email": "samumartineau@gmail.com",
            "name": "Samuel-Martineau"
          },
          "message": "Modification de la liste des repos",
          "distinct": true,
          "url": "https://api.github.com/repos/Samuel-Martineau/Smartineau.me/commits/b59b7357f08b85a29c9a5c1a7c7abfd7abe66fa5"
        },
        {
          "sha": "061cb7b41f0f98c02f77af438b0aa4e1ed73d547",
          "author": {
            "email": "samumartineau@gmail.com",
            "name": "Samuel-Martineau"
          },
          "message": "Modification de la liste des repos",
          "distinct": true,
          "url": "https://api.github.com/repos/Samuel-Martineau/Smartineau.me/commits/061cb7b41f0f98c02f77af438b0aa4e1ed73d547"
        }
      ]
    },
    "public": true,
    "created_at": "2020-07-20T20:38:36Z"
  },
  {
    "id": "12964491768",
    "type": "PushEvent",
    "actor": {
      "id": 44237969,
      "login": "Samuel-Martineau",
      "display_login": "Samuel-Martineau",
      "gravatar_id": "",
      "url": "https://api.github.com/users/Samuel-Martineau",
      "avatar_url": "https://avatars.githubusercontent.com/u/44237969?"
    },
    "repo": {
      "id": 278900496,
      "name": "Samuel-Martineau/Samuel-Martineau",
      "url": "https://api.github.com/repos/Samuel-Martineau/Samuel-Martineau"
    },
    "payload": {
      "push_id": 5404575493,
      "size": 1,
      "distinct_size": 1,
      "ref": "refs/heads/master",
      "head": "5b09e18bce04ffae8ecb493fe3149e4f805ad12c",
      "before": "5df30b54a8d807980e30688c525661555f7eecd5",
      "commits": [
        {
          "sha": "5b09e18bce04ffae8ecb493fe3149e4f805ad12c",
          "author": {
            "email": "samumartineau@gmail.com",
            "name": "Samuel-Martineau"
          },
          "message": "Modification du README",
          "distinct": true,
          "url": "https://api.github.com/repos/Samuel-Martineau/Samuel-Martineau/commits/5b09e18bce04ffae8ecb493fe3149e4f805ad12c"
        }
      ]
    },
    "public": true,
    "created_at": "2020-07-20T20:35:14Z"
  },
  {
    "id": "12964482457",
    "type": "PushEvent",
    "actor": {
      "id": 44237969,
      "login": "Samuel-Martineau",
      "display_login": "Samuel-Martineau",
      "gravatar_id": "",
      "url": "https://api.github.com/users/Samuel-Martineau",
      "avatar_url": "https://avatars.githubusercontent.com/u/44237969?"
    },
    "repo": {
      "id": 278900496,
      "name": "Samuel-Martineau/Samuel-Martineau",
      "url": "https://api.github.com/repos/Samuel-Martineau/Samuel-Martineau"
    },
    "payload": {
      "push_id": 5404570961,
      "size": 1,
      "distinct_size": 1,
      "ref": "refs/heads/master",
      "head": "5df30b54a8d807980e30688c525661555f7eecd5",
      "before": "6f90e3f82d551bfb652d030b6095fb545e44cdd1",
      "commits": [
        {
          "sha": "5df30b54a8d807980e30688c525661555f7eecd5",
          "author": {
            "email": "samumartineau@gmail.com",
            "name": "Samuel-Martineau"
          },
          "message": "Modification du README",
          "distinct": true,
          "url": "https://api.github.com/repos/Samuel-Martineau/Samuel-Martineau/commits/5df30b54a8d807980e30688c525661555f7eecd5"
        }
      ]
    },
    "public": true,
    "created_at": "2020-07-20T20:34:14Z"
  },
  {
    "id": "12964470210",
    "type": "PushEvent",
    "actor": {
      "id": 44237969,
      "login": "Samuel-Martineau",
      "display_login": "Samuel-Martineau",
      "gravatar_id": "",
      "url": "https://api.github.com/users/Samuel-Martineau",
      "avatar_url": "https://avatars.githubusercontent.com/u/44237969?"
    },
    "repo": {
      "id": 279429394,
      "name": "Samuel-Martineau/Smartineau.me",
      "url": "https://api.github.com/repos/Samuel-Martineau/Smartineau.me"
    },
    "payload": {
      "push_id": 5404565050,
      "size": 1,
      "distinct_size": 1,
      "ref": "refs/heads/master",
      "head": "3a2666c7257e247611be794245446664d06c6875",
      "before": "cb71ce62aee304e3dc4636c5594f790e297abf8b",
      "commits": [
        {
          "sha": "3a2666c7257e247611be794245446664d06c6875",
          "author": {
            "email": "samumartineau@gmail.com",
            "name": "Samuel Martineau"
          },
          "message": "Update repos.json",
          "distinct": true,
          "url": "https://api.github.com/repos/Samuel-Martineau/Smartineau.me/commits/3a2666c7257e247611be794245446664d06c6875"
        }
      ]
    },
    "public": true,
    "created_at": "2020-07-20T20:33:00Z"
  },
  {
    "id": "12964390809",
    "type": "PushEvent",
    "actor": {
      "id": 44237969,
      "login": "Samuel-Martineau",
      "display_login": "Samuel-Martineau",
      "gravatar_id": "",
      "url": "https://api.github.com/users/Samuel-Martineau",
      "avatar_url": "https://avatars.githubusercontent.com/u/44237969?"
    },
    "repo": {
      "id": 278900496,
      "name": "Samuel-Martineau/Samuel-Martineau",
      "url": "https://api.github.com/repos/Samuel-Martineau/Samuel-Martineau"
    },
    "payload": {
      "push_id": 5404526924,
      "size": 1,
      "distinct_size": 1,
      "ref": "refs/heads/master",
      "head": "6f90e3f82d551bfb652d030b6095fb545e44cdd1",
      "before": "3f2fda4f6a6a08d133a0e0c0870d5aadda08d8a8",
      "commits": [
        {
          "sha": "6f90e3f82d551bfb652d030b6095fb545e44cdd1",
          "author": {
            "email": "samumartineau@gmail.com",
            "name": "Samuel-Martineau"
          },
          "message": "Modification du README",
          "distinct": true,
          "url": "https://api.github.com/repos/Samuel-Martineau/Samuel-Martineau/commits/6f90e3f82d551bfb652d030b6095fb545e44cdd1"
        }
      ]
    },
    "public": true,
    "created_at": "2020-07-20T20:24:45Z"
  },
  {
    "id": "12964381014",
    "type": "PushEvent",
    "actor": {
      "id": 44237969,
      "login": "Samuel-Martineau",
      "display_login": "Samuel-Martineau",
      "gravatar_id": "",
      "url": "https://api.github.com/users/Samuel-Martineau",
      "avatar_url": "https://avatars.githubusercontent.com/u/44237969?"
    },
    "repo": {
      "id": 278900496,
      "name": "Samuel-Martineau/Samuel-Martineau",
      "url": "https://api.github.com/repos/Samuel-Martineau/Samuel-Martineau"
    },
    "payload": {
      "push_id": 5404522222,
      "size": 1,
      "distinct_size": 1,
      "ref": "refs/heads/master",
      "head": "3f2fda4f6a6a08d133a0e0c0870d5aadda08d8a8",
      "before": "1bc20942b0ae1be30b6630880e76f3883d82fe18",
      "commits": [
        {
          "sha": "3f2fda4f6a6a08d133a0e0c0870d5aadda08d8a8",
          "author": {
            "email": "samumartineau@gmail.com",
            "name": "Samuel-Martineau"
          },
          "message": "Modification du README",
          "distinct": true,
          "url": "https://api.github.com/repos/Samuel-Martineau/Samuel-Martineau/commits/3f2fda4f6a6a08d133a0e0c0870d5aadda08d8a8"
        }
      ]
    },
    "public": true,
    "created_at": "2020-07-20T20:23:43Z"
  },
  {
    "id": "12964377881",
    "type": "PushEvent",
    "actor": {
      "id": 44237969,
      "login": "Samuel-Martineau",
      "display_login": "Samuel-Martineau",
      "gravatar_id": "",
      "url": "https://api.github.com/users/Samuel-Martineau",
      "avatar_url": "https://avatars.githubusercontent.com/u/44237969?"
    },
    "repo": {
      "id": 278900496,
      "name": "Samuel-Martineau/Samuel-Martineau",
      "url": "https://api.github.com/repos/Samuel-Martineau/Samuel-Martineau"
    },
    "payload": {
      "push_id": 5404520743,
      "size": 1,
      "distinct_size": 1,
      "ref": "refs/heads/master",
      "head": "1bc20942b0ae1be30b6630880e76f3883d82fe18",
      "before": "ee05123588dfbc18b41a78ca99335ca77868c081",
      "commits": [
        {
          "sha": "1bc20942b0ae1be30b6630880e76f3883d82fe18",
          "author": {
            "email": "samumartineau@gmail.com",
            "name": "Samuel-Martineau"
          },
          "message": "Modification du README",
          "distinct": true,
          "url": "https://api.github.com/repos/Samuel-Martineau/Samuel-Martineau/commits/1bc20942b0ae1be30b6630880e76f3883d82fe18"
        }
      ]
    },
    "public": true,
    "created_at": "2020-07-20T20:23:22Z"
  },
  {
    "id": "12964336724",
    "type": "PushEvent",
    "actor": {
      "id": 44237969,
      "login": "Samuel-Martineau",
      "display_login": "Samuel-Martineau",
      "gravatar_id": "",
      "url": "https://api.github.com/users/Samuel-Martineau",
      "avatar_url": "https://avatars.githubusercontent.com/u/44237969?"
    },
    "repo": {
      "id": 278900496,
      "name": "Samuel-Martineau/Samuel-Martineau",
      "url": "https://api.github.com/repos/Samuel-Martineau/Samuel-Martineau"
    },
    "payload": {
      "push_id": 5404500647,
      "size": 2,
      "distinct_size": 2,
      "ref": "refs/heads/master",
      "head": "ee05123588dfbc18b41a78ca99335ca77868c081",
      "before": "49e1754cf543c512f63688500ff89c93412a203f",
      "commits": [
        {
          "sha": "45d0f6b03603f01f27df5913ce4b0e9ae8413597",
          "author": {
            "email": "samumartineau@gmail.com",
            "name": "Samuel-Martineau"
          },
          "message": "Modification du README",
          "distinct": true,
          "url": "https://api.github.com/repos/Samuel-Martineau/Samuel-Martineau/commits/45d0f6b03603f01f27df5913ce4b0e9ae8413597"
        },
        {
          "sha": "ee05123588dfbc18b41a78ca99335ca77868c081",
          "author": {
            "email": "samumartineau@gmail.com",
            "name": "Samuel-Martineau"
          },
          "message": "Modification du README",
          "distinct": true,
          "url": "https://api.github.com/repos/Samuel-Martineau/Samuel-Martineau/commits/ee05123588dfbc18b41a78ca99335ca77868c081"
        }
      ]
    },
    "public": true,
    "created_at": "2020-07-20T20:19:02Z"
  },
  {
    "id": "12964167940",
    "type": "PushEvent",
    "actor": {
      "id": 44237969,
      "login": "Samuel-Martineau",
      "display_login": "Samuel-Martineau",
      "gravatar_id": "",
      "url": "https://api.github.com/users/Samuel-Martineau",
      "avatar_url": "https://avatars.githubusercontent.com/u/44237969?"
    },
    "repo": {
      "id": 278900496,
      "name": "Samuel-Martineau/Samuel-Martineau",
      "url": "https://api.github.com/repos/Samuel-Martineau/Samuel-Martineau"
    },
    "payload": {
      "push_id": 5404418063,
      "size": 1,
      "distinct_size": 1,
      "ref": "refs/heads/master",
      "head": "49e1754cf543c512f63688500ff89c93412a203f",
      "before": "86db1124d5f50797298f6caca0ab946cd01ee078",
      "commits": [
        {
          "sha": "49e1754cf543c512f63688500ff89c93412a203f",
          "author": {
            "email": "samumartineau@gmail.com",
            "name": "Samuel-Martineau"
          },
          "message": "Modification du README",
          "distinct": true,
          "url": "https://api.github.com/repos/Samuel-Martineau/Samuel-Martineau/commits/49e1754cf543c512f63688500ff89c93412a203f"
        }
      ]
    },
    "public": true,
    "created_at": "2020-07-20T20:01:21Z"
  },
  {
    "id": "12964163465",
    "type": "PushEvent",
    "actor": {
      "id": 44237969,
      "login": "Samuel-Martineau",
      "display_login": "Samuel-Martineau",
      "gravatar_id": "",
      "url": "https://api.github.com/users/Samuel-Martineau",
      "avatar_url": "https://avatars.githubusercontent.com/u/44237969?"
    },
    "repo": {
      "id": 278900496,
      "name": "Samuel-Martineau/Samuel-Martineau",
      "url": "https://api.github.com/repos/Samuel-Martineau/Samuel-Martineau"
    },
    "payload": {
      "push_id": 5404415786,
      "size": 1,
      "distinct_size": 1,
      "ref": "refs/heads/master",
      "head": "86db1124d5f50797298f6caca0ab946cd01ee078",
      "before": "49520f2a419d2fc43288b3eecade53da284f0169",
      "commits": [
        {
          "sha": "86db1124d5f50797298f6caca0ab946cd01ee078",
          "author": {
            "email": "samumartineau@gmail.com",
            "name": "Samuel-Martineau"
          },
          "message": "Modification du README",
          "distinct": true,
          "url": "https://api.github.com/repos/Samuel-Martineau/Samuel-Martineau/commits/86db1124d5f50797298f6caca0ab946cd01ee078"
        }
      ]
    },
    "public": true,
    "created_at": "2020-07-20T20:00:53Z"
  },
  {
    "id": "12964158510",
    "type": "PushEvent",
    "actor": {
      "id": 44237969,
      "login": "Samuel-Martineau",
      "display_login": "Samuel-Martineau",
      "gravatar_id": "",
      "url": "https://api.github.com/users/Samuel-Martineau",
      "avatar_url": "https://avatars.githubusercontent.com/u/44237969?"
    },
    "repo": {
      "id": 278900496,
      "name": "Samuel-Martineau/Samuel-Martineau",
      "url": "https://api.github.com/repos/Samuel-Martineau/Samuel-Martineau"
    },
    "payload": {
      "push_id": 5404413289,
      "size": 1,
      "distinct_size": 1,
      "ref": "refs/heads/master",
      "head": "49520f2a419d2fc43288b3eecade53da284f0169",
      "before": "696abf6fa9b8acda988bf8735edc424deb11049a",
      "commits": [
        {
          "sha": "49520f2a419d2fc43288b3eecade53da284f0169",
          "author": {
            "email": "samumartineau@gmail.com",
            "name": "Samuel-Martineau"
          },
          "message": "Modification du README",
          "distinct": true,
          "url": "https://api.github.com/repos/Samuel-Martineau/Samuel-Martineau/commits/49520f2a419d2fc43288b3eecade53da284f0169"
        }
      ]
    },
    "public": true,
    "created_at": "2020-07-20T20:00:24Z"
  },
  {
    "id": "12964138663",
    "type": "PushEvent",
    "actor": {
      "id": 44237969,
      "login": "Samuel-Martineau",
      "display_login": "Samuel-Martineau",
      "gravatar_id": "",
      "url": "https://api.github.com/users/Samuel-Martineau",
      "avatar_url": "https://avatars.githubusercontent.com/u/44237969?"
    },
    "repo": {
      "id": 278900496,
      "name": "Samuel-Martineau/Samuel-Martineau",
      "url": "https://api.github.com/repos/Samuel-Martineau/Samuel-Martineau"
    },
    "payload": {
      "push_id": 5404403202,
      "size": 1,
      "distinct_size": 1,
      "ref": "refs/heads/master",
      "head": "696abf6fa9b8acda988bf8735edc424deb11049a",
      "before": "762ddd7b09090f01f8ef6df83865ef67dbe21049",
      "commits": [
        {
          "sha": "696abf6fa9b8acda988bf8735edc424deb11049a",
          "author": {
            "email": "samumartineau@gmail.com",
            "name": "Samuel-Martineau"
          },
          "message": "Modification du README",
          "distinct": true,
          "url": "https://api.github.com/repos/Samuel-Martineau/Samuel-Martineau/commits/696abf6fa9b8acda988bf8735edc424deb11049a"
        }
      ]
    },
    "public": true,
    "created_at": "2020-07-20T19:58:23Z"
  },
  {
    "id": "12964125353",
    "type": "PushEvent",
    "actor": {
      "id": 44237969,
      "login": "Samuel-Martineau",
      "display_login": "Samuel-Martineau",
      "gravatar_id": "",
      "url": "https://api.github.com/users/Samuel-Martineau",
      "avatar_url": "https://avatars.githubusercontent.com/u/44237969?"
    },
    "repo": {
      "id": 278900496,
      "name": "Samuel-Martineau/Samuel-Martineau",
      "url": "https://api.github.com/repos/Samuel-Martineau/Samuel-Martineau"
    },
    "payload": {
      "push_id": 5404396841,
      "size": 1,
      "distinct_size": 1,
      "ref": "refs/heads/master",
      "head": "762ddd7b09090f01f8ef6df83865ef67dbe21049",
      "before": "1ad8c3a70b9dc909fe226546ee12fad5d3fd3e4c",
      "commits": [
        {
          "sha": "762ddd7b09090f01f8ef6df83865ef67dbe21049",
          "author": {
            "email": "samumartineau@gmail.com",
            "name": "Samuel-Martineau"
          },
          "message": "Modification du README",
          "distinct": true,
          "url": "https://api.github.com/repos/Samuel-Martineau/Samuel-Martineau/commits/762ddd7b09090f01f8ef6df83865ef67dbe21049"
        }
      ]
    },
    "public": true,
    "created_at": "2020-07-20T19:57:00Z"
  },
  {
    "id": "12964120243",
    "type": "PushEvent",
    "actor": {
      "id": 44237969,
      "login": "Samuel-Martineau",
      "display_login": "Samuel-Martineau",
      "gravatar_id": "",
      "url": "https://api.github.com/users/Samuel-Martineau",
      "avatar_url": "https://avatars.githubusercontent.com/u/44237969?"
    },
    "repo": {
      "id": 278900496,
      "name": "Samuel-Martineau/Samuel-Martineau",
      "url": "https://api.github.com/repos/Samuel-Martineau/Samuel-Martineau"
    },
    "payload": {
      "push_id": 5404394397,
      "size": 1,
      "distinct_size": 1,
      "ref": "refs/heads/master",
      "head": "1ad8c3a70b9dc909fe226546ee12fad5d3fd3e4c",
      "before": "c6a83c898806d7de6b55510da7544d70ff00bcf0",
      "commits": [
        {
          "sha": "1ad8c3a70b9dc909fe226546ee12fad5d3fd3e4c",
          "author": {
            "email": "samumartineau@gmail.com",
            "name": "Samuel-Martineau"
          },
          "message": "Premier commit",
          "distinct": true,
          "url": "https://api.github.com/repos/Samuel-Martineau/Samuel-Martineau/commits/1ad8c3a70b9dc909fe226546ee12fad5d3fd3e4c"
        }
      ]
    },
    "public": true,
    "created_at": "2020-07-20T19:56:28Z"
  },
  {
    "id": "12964086154",
    "type": "PushEvent",
    "actor": {
      "id": 44237969,
      "login": "Samuel-Martineau",
      "display_login": "Samuel-Martineau",
      "gravatar_id": "",
      "url": "https://api.github.com/users/Samuel-Martineau",
      "avatar_url": "https://avatars.githubusercontent.com/u/44237969?"
    },
    "repo": {
      "id": 278900496,
      "name": "Samuel-Martineau/Samuel-Martineau",
      "url": "https://api.github.com/repos/Samuel-Martineau/Samuel-Martineau"
    },
    "payload": {
      "push_id": 5404377613,
      "size": 1,
      "distinct_size": 1,
      "ref": "refs/heads/master",
      "head": "c6a83c898806d7de6b55510da7544d70ff00bcf0",
      "before": "1d5ea6bf44ebbbbfd27e51cff219d94714ed1504",
      "commits": [
        {
          "sha": "c6a83c898806d7de6b55510da7544d70ff00bcf0",
          "author": {
            "email": "samumartineau@gmail.com",
            "name": "Samuel Martineau"
          },
          "message": "Delete README.md",
          "distinct": true,
          "url": "https://api.github.com/repos/Samuel-Martineau/Samuel-Martineau/commits/c6a83c898806d7de6b55510da7544d70ff00bcf0"
        }
      ]
    },
    "public": true,
    "created_at": "2020-07-20T19:52:51Z"
  },
  {
    "id": "12963307904",
    "type": "PullRequestEvent",
    "actor": {
      "id": 44237969,
      "login": "Samuel-Martineau",
      "display_login": "Samuel-Martineau",
      "gravatar_id": "",
      "url": "https://api.github.com/users/Samuel-Martineau",
      "avatar_url": "https://avatars.githubusercontent.com/u/44237969?"
    },
    "repo": {
      "id": 280742722,
      "name": "Samuel-Martineau/Potions-HUD-Fabric",
      "url": "https://api.github.com/repos/Samuel-Martineau/Potions-HUD-Fabric"
    },
    "payload": {
      "action": "closed",
      "number": 1,
      "pull_request": {
        "url": "https://api.github.com/repos/Samuel-Martineau/Potions-HUD-Fabric/pulls/1",
        "id": 453718964,
        "node_id": "MDExOlB1bGxSZXF1ZXN0NDUzNzE4OTY0",
        "html_url": "https://github.com/Samuel-Martineau/Potions-HUD-Fabric/pull/1",
        "diff_url": "https://github.com/Samuel-Martineau/Potions-HUD-Fabric/pull/1.diff",
        "patch_url": "https://github.com/Samuel-Martineau/Potions-HUD-Fabric/pull/1.patch",
        "issue_url": "https://api.github.com/repos/Samuel-Martineau/Potions-HUD-Fabric/issues/1",
        "number": 1,
        "state": "closed",
        "locked": false,
        "title": "Logo change",
        "user": {
          "login": "Doudou8",
          "id": 49688773,
          "node_id": "MDQ6VXNlcjQ5Njg4Nzcz",
          "avatar_url": "https://avatars2.githubusercontent.com/u/49688773?v=4",
          "gravatar_id": "",
          "url": "https://api.github.com/users/Doudou8",
          "html_url": "https://github.com/Doudou8",
          "followers_url": "https://api.github.com/users/Doudou8/followers",
          "following_url": "https://api.github.com/users/Doudou8/following{/other_user}",
          "gists_url": "https://api.github.com/users/Doudou8/gists{/gist_id}",
          "starred_url": "https://api.github.com/users/Doudou8/starred{/owner}{/repo}",
          "subscriptions_url": "https://api.github.com/users/Doudou8/subscriptions",
          "organizations_url": "https://api.github.com/users/Doudou8/orgs",
          "repos_url": "https://api.github.com/users/Doudou8/repos",
          "events_url": "https://api.github.com/users/Doudou8/events{/privacy}",
          "received_events_url": "https://api.github.com/users/Doudou8/received_events",
          "type": "User",
          "site_admin": false
        },
        "body": "",
        "created_at": "2020-07-20T18:33:43Z",
        "updated_at": "2020-07-20T18:34:24Z",
        "closed_at": "2020-07-20T18:34:24Z",
        "merged_at": "2020-07-20T18:34:24Z",
        "merge_commit_sha": "c848859fde8dbfd5da4c67c68232fb9063c3f83c",
        "assignee": null,
        "assignees": [],
        "requested_reviewers": [],
        "requested_teams": [],
        "labels": [],
        "milestone": null,
        "draft": false,
        "commits_url": "https://api.github.com/repos/Samuel-Martineau/Potions-HUD-Fabric/pulls/1/commits",
        "review_comments_url": "https://api.github.com/repos/Samuel-Martineau/Potions-HUD-Fabric/pulls/1/comments",
        "review_comment_url": "https://api.github.com/repos/Samuel-Martineau/Potions-HUD-Fabric/pulls/comments{/number}",
        "comments_url": "https://api.github.com/repos/Samuel-Martineau/Potions-HUD-Fabric/issues/1/comments",
        "statuses_url": "https://api.github.com/repos/Samuel-Martineau/Potions-HUD-Fabric/statuses/32bdf4c9411a9ed8034381a1c53c560fdd87fd2b",
        "head": {
          "label": "Doudou8:master",
          "ref": "master",
          "sha": "32bdf4c9411a9ed8034381a1c53c560fdd87fd2b",
          "user": {
            "login": "Doudou8",
            "id": 49688773,
            "node_id": "MDQ6VXNlcjQ5Njg4Nzcz",
            "avatar_url": "https://avatars2.githubusercontent.com/u/49688773?v=4",
            "gravatar_id": "",
            "url": "https://api.github.com/users/Doudou8",
            "html_url": "https://github.com/Doudou8",
            "followers_url": "https://api.github.com/users/Doudou8/followers",
            "following_url": "https://api.github.com/users/Doudou8/following{/other_user}",
            "gists_url": "https://api.github.com/users/Doudou8/gists{/gist_id}",
            "starred_url": "https://api.github.com/users/Doudou8/starred{/owner}{/repo}",
            "subscriptions_url": "https://api.github.com/users/Doudou8/subscriptions",
            "organizations_url": "https://api.github.com/users/Doudou8/orgs",
            "repos_url": "https://api.github.com/users/Doudou8/repos",
            "events_url": "https://api.github.com/users/Doudou8/events{/privacy}",
            "received_events_url": "https://api.github.com/users/Doudou8/received_events",
            "type": "User",
            "site_admin": false
          },
          "repo": {
            "id": 281195411,
            "node_id": "MDEwOlJlcG9zaXRvcnkyODExOTU0MTE=",
            "name": "Potions-HUD-Fabric",
            "full_name": "Doudou8/Potions-HUD-Fabric",
            "private": false,
            "owner": {
              "login": "Doudou8",
              "id": 49688773,
              "node_id": "MDQ6VXNlcjQ5Njg4Nzcz",
              "avatar_url": "https://avatars2.githubusercontent.com/u/49688773?v=4",
              "gravatar_id": "",
              "url": "https://api.github.com/users/Doudou8",
              "html_url": "https://github.com/Doudou8",
              "followers_url": "https://api.github.com/users/Doudou8/followers",
              "following_url": "https://api.github.com/users/Doudou8/following{/other_user}",
              "gists_url": "https://api.github.com/users/Doudou8/gists{/gist_id}",
              "starred_url": "https://api.github.com/users/Doudou8/starred{/owner}{/repo}",
              "subscriptions_url": "https://api.github.com/users/Doudou8/subscriptions",
              "organizations_url": "https://api.github.com/users/Doudou8/orgs",
              "repos_url": "https://api.github.com/users/Doudou8/repos",
              "events_url": "https://api.github.com/users/Doudou8/events{/privacy}",
              "received_events_url": "https://api.github.com/users/Doudou8/received_events",
              "type": "User",
              "site_admin": false
            },
            "html_url": "https://github.com/Doudou8/Potions-HUD-Fabric",
            "description": "A simple mod that displays the current potion (status) effects on the HUD for Fabric 1.16.1",
            "fork": true,
            "url": "https://api.github.com/repos/Doudou8/Potions-HUD-Fabric",
            "forks_url": "https://api.github.com/repos/Doudou8/Potions-HUD-Fabric/forks",
            "keys_url": "https://api.github.com/repos/Doudou8/Potions-HUD-Fabric/keys{/key_id}",
            "collaborators_url": "https://api.github.com/repos/Doudou8/Potions-HUD-Fabric/collaborators{/collaborator}",
            "teams_url": "https://api.github.com/repos/Doudou8/Potions-HUD-Fabric/teams",
            "hooks_url": "https://api.github.com/repos/Doudou8/Potions-HUD-Fabric/hooks",
            "issue_events_url": "https://api.github.com/repos/Doudou8/Potions-HUD-Fabric/issues/events{/number}",
            "events_url": "https://api.github.com/repos/Doudou8/Potions-HUD-Fabric/events",
            "assignees_url": "https://api.github.com/repos/Doudou8/Potions-HUD-Fabric/assignees{/user}",
            "branches_url": "https://api.github.com/repos/Doudou8/Potions-HUD-Fabric/branches{/branch}",
            "tags_url": "https://api.github.com/repos/Doudou8/Potions-HUD-Fabric/tags",
            "blobs_url": "https://api.github.com/repos/Doudou8/Potions-HUD-Fabric/git/blobs{/sha}",
            "git_tags_url": "https://api.github.com/repos/Doudou8/Potions-HUD-Fabric/git/tags{/sha}",
            "git_refs_url": "https://api.github.com/repos/Doudou8/Potions-HUD-Fabric/git/refs{/sha}",
            "trees_url": "https://api.github.com/repos/Doudou8/Potions-HUD-Fabric/git/trees{/sha}",
            "statuses_url": "https://api.github.com/repos/Doudou8/Potions-HUD-Fabric/statuses/{sha}",
            "languages_url": "https://api.github.com/repos/Doudou8/Potions-HUD-Fabric/languages",
            "stargazers_url": "https://api.github.com/repos/Doudou8/Potions-HUD-Fabric/stargazers",
            "contributors_url": "https://api.github.com/repos/Doudou8/Potions-HUD-Fabric/contributors",
            "subscribers_url": "https://api.github.com/repos/Doudou8/Potions-HUD-Fabric/subscribers",
            "subscription_url": "https://api.github.com/repos/Doudou8/Potions-HUD-Fabric/subscription",
            "commits_url": "https://api.github.com/repos/Doudou8/Potions-HUD-Fabric/commits{/sha}",
            "git_commits_url": "https://api.github.com/repos/Doudou8/Potions-HUD-Fabric/git/commits{/sha}",
            "comments_url": "https://api.github.com/repos/Doudou8/Potions-HUD-Fabric/comments{/number}",
            "issue_comment_url": "https://api.github.com/repos/Doudou8/Potions-HUD-Fabric/issues/comments{/number}",
            "contents_url": "https://api.github.com/repos/Doudou8/Potions-HUD-Fabric/contents/{+path}",
            "compare_url": "https://api.github.com/repos/Doudou8/Potions-HUD-Fabric/compare/{base}...{head}",
            "merges_url": "https://api.github.com/repos/Doudou8/Potions-HUD-Fabric/merges",
            "archive_url": "https://api.github.com/repos/Doudou8/Potions-HUD-Fabric/{archive_format}{/ref}",
            "downloads_url": "https://api.github.com/repos/Doudou8/Potions-HUD-Fabric/downloads",
            "issues_url": "https://api.github.com/repos/Doudou8/Potions-HUD-Fabric/issues{/number}",
            "pulls_url": "https://api.github.com/repos/Doudou8/Potions-HUD-Fabric/pulls{/number}",
            "milestones_url": "https://api.github.com/repos/Doudou8/Potions-HUD-Fabric/milestones{/number}",
            "notifications_url": "https://api.github.com/repos/Doudou8/Potions-HUD-Fabric/notifications{?since,all,participating}",
            "labels_url": "https://api.github.com/repos/Doudou8/Potions-HUD-Fabric/labels{/name}",
            "releases_url": "https://api.github.com/repos/Doudou8/Potions-HUD-Fabric/releases{/id}",
            "deployments_url": "https://api.github.com/repos/Doudou8/Potions-HUD-Fabric/deployments",
            "created_at": "2020-07-20T18:27:04Z",
            "updated_at": "2020-07-20T18:32:31Z",
            "pushed_at": "2020-07-20T18:32:28Z",
            "git_url": "git://github.com/Doudou8/Potions-HUD-Fabric.git",
            "ssh_url": "git@github.com:Doudou8/Potions-HUD-Fabric.git",
            "clone_url": "https://github.com/Doudou8/Potions-HUD-Fabric.git",
            "svn_url": "https://github.com/Doudou8/Potions-HUD-Fabric",
            "homepage": "",
            "size": 3139,
            "stargazers_count": 0,
            "watchers_count": 0,
            "language": "Java",
            "has_issues": false,
            "has_projects": true,
            "has_downloads": true,
            "has_wiki": true,
            "has_pages": false,
            "forks_count": 0,
            "mirror_url": null,
            "archived": false,
            "disabled": false,
            "open_issues_count": 0,
            "license": {
              "key": "mit",
              "name": "MIT License",
              "spdx_id": "MIT",
              "url": "https://api.github.com/licenses/mit",
              "node_id": "MDc6TGljZW5zZTEz"
            },
            "forks": 0,
            "open_issues": 0,
            "watchers": 0,
            "default_branch": "master"
          }
        },
        "base": {
          "label": "Samuel-Martineau:master",
          "ref": "master",
          "sha": "cffa02dcc0fa9d3f9703abaee7d24fe11f63a573",
          "user": {
            "login": "Samuel-Martineau",
            "id": 44237969,
            "node_id": "MDQ6VXNlcjQ0MjM3OTY5",
            "avatar_url": "https://avatars3.githubusercontent.com/u/44237969?v=4",
            "gravatar_id": "",
            "url": "https://api.github.com/users/Samuel-Martineau",
            "html_url": "https://github.com/Samuel-Martineau",
            "followers_url": "https://api.github.com/users/Samuel-Martineau/followers",
            "following_url": "https://api.github.com/users/Samuel-Martineau/following{/other_user}",
            "gists_url": "https://api.github.com/users/Samuel-Martineau/gists{/gist_id}",
            "starred_url": "https://api.github.com/users/Samuel-Martineau/starred{/owner}{/repo}",
            "subscriptions_url": "https://api.github.com/users/Samuel-Martineau/subscriptions",
            "organizations_url": "https://api.github.com/users/Samuel-Martineau/orgs",
            "repos_url": "https://api.github.com/users/Samuel-Martineau/repos",
            "events_url": "https://api.github.com/users/Samuel-Martineau/events{/privacy}",
            "received_events_url": "https://api.github.com/users/Samuel-Martineau/received_events",
            "type": "User",
            "site_admin": false
          },
          "repo": {
            "id": 280742722,
            "node_id": "MDEwOlJlcG9zaXRvcnkyODA3NDI3MjI=",
            "name": "Potions-HUD-Fabric",
            "full_name": "Samuel-Martineau/Potions-HUD-Fabric",
            "private": false,
            "owner": {
              "login": "Samuel-Martineau",
              "id": 44237969,
              "node_id": "MDQ6VXNlcjQ0MjM3OTY5",
              "avatar_url": "https://avatars3.githubusercontent.com/u/44237969?v=4",
              "gravatar_id": "",
              "url": "https://api.github.com/users/Samuel-Martineau",
              "html_url": "https://github.com/Samuel-Martineau",
              "followers_url": "https://api.github.com/users/Samuel-Martineau/followers",
              "following_url": "https://api.github.com/users/Samuel-Martineau/following{/other_user}",
              "gists_url": "https://api.github.com/users/Samuel-Martineau/gists{/gist_id}",
              "starred_url": "https://api.github.com/users/Samuel-Martineau/starred{/owner}{/repo}",
              "subscriptions_url": "https://api.github.com/users/Samuel-Martineau/subscriptions",
              "organizations_url": "https://api.github.com/users/Samuel-Martineau/orgs",
              "repos_url": "https://api.github.com/users/Samuel-Martineau/repos",
              "events_url": "https://api.github.com/users/Samuel-Martineau/events{/privacy}",
              "received_events_url": "https://api.github.com/users/Samuel-Martineau/received_events",
              "type": "User",
              "site_admin": false
            },
            "html_url": "https://github.com/Samuel-Martineau/Potions-HUD-Fabric",
            "description": "A simple mod that displays the current potion (status) effects on the HUD for Fabric 1.16.1",
            "fork": false,
            "url": "https://api.github.com/repos/Samuel-Martineau/Potions-HUD-Fabric",
            "forks_url": "https://api.github.com/repos/Samuel-Martineau/Potions-HUD-Fabric/forks",
            "keys_url": "https://api.github.com/repos/Samuel-Martineau/Potions-HUD-Fabric/keys{/key_id}",
            "collaborators_url": "https://api.github.com/repos/Samuel-Martineau/Potions-HUD-Fabric/collaborators{/collaborator}",
            "teams_url": "https://api.github.com/repos/Samuel-Martineau/Potions-HUD-Fabric/teams",
            "hooks_url": "https://api.github.com/repos/Samuel-Martineau/Potions-HUD-Fabric/hooks",
            "issue_events_url": "https://api.github.com/repos/Samuel-Martineau/Potions-HUD-Fabric/issues/events{/number}",
            "events_url": "https://api.github.com/repos/Samuel-Martineau/Potions-HUD-Fabric/events",
            "assignees_url": "https://api.github.com/repos/Samuel-Martineau/Potions-HUD-Fabric/assignees{/user}",
            "branches_url": "https://api.github.com/repos/Samuel-Martineau/Potions-HUD-Fabric/branches{/branch}",
            "tags_url": "https://api.github.com/repos/Samuel-Martineau/Potions-HUD-Fabric/tags",
            "blobs_url": "https://api.github.com/repos/Samuel-Martineau/Potions-HUD-Fabric/git/blobs{/sha}",
            "git_tags_url": "https://api.github.com/repos/Samuel-Martineau/Potions-HUD-Fabric/git/tags{/sha}",
            "git_refs_url": "https://api.github.com/repos/Samuel-Martineau/Potions-HUD-Fabric/git/refs{/sha}",
            "trees_url": "https://api.github.com/repos/Samuel-Martineau/Potions-HUD-Fabric/git/trees{/sha}",
            "statuses_url": "https://api.github.com/repos/Samuel-Martineau/Potions-HUD-Fabric/statuses/{sha}",
            "languages_url": "https://api.github.com/repos/Samuel-Martineau/Potions-HUD-Fabric/languages",
            "stargazers_url": "https://api.github.com/repos/Samuel-Martineau/Potions-HUD-Fabric/stargazers",
            "contributors_url": "https://api.github.com/repos/Samuel-Martineau/Potions-HUD-Fabric/contributors",
            "subscribers_url": "https://api.github.com/repos/Samuel-Martineau/Potions-HUD-Fabric/subscribers",
            "subscription_url": "https://api.github.com/repos/Samuel-Martineau/Potions-HUD-Fabric/subscription",
            "commits_url": "https://api.github.com/repos/Samuel-Martineau/Potions-HUD-Fabric/commits{/sha}",
            "git_commits_url": "https://api.github.com/repos/Samuel-Martineau/Potions-HUD-Fabric/git/commits{/sha}",
            "comments_url": "https://api.github.com/repos/Samuel-Martineau/Potions-HUD-Fabric/comments{/number}",
            "issue_comment_url": "https://api.github.com/repos/Samuel-Martineau/Potions-HUD-Fabric/issues/comments{/number}",
            "contents_url": "https://api.github.com/repos/Samuel-Martineau/Potions-HUD-Fabric/contents/{+path}",
            "compare_url": "https://api.github.com/repos/Samuel-Martineau/Potions-HUD-Fabric/compare/{base}...{head}",
            "merges_url": "https://api.github.com/repos/Samuel-Martineau/Potions-HUD-Fabric/merges",
            "archive_url": "https://api.github.com/repos/Samuel-Martineau/Potions-HUD-Fabric/{archive_format}{/ref}",
            "downloads_url": "https://api.github.com/repos/Samuel-Martineau/Potions-HUD-Fabric/downloads",
            "issues_url": "https://api.github.com/repos/Samuel-Martineau/Potions-HUD-Fabric/issues{/number}",
            "pulls_url": "https://api.github.com/repos/Samuel-Martineau/Potions-HUD-Fabric/pulls{/number}",
            "milestones_url": "https://api.github.com/repos/Samuel-Martineau/Potions-HUD-Fabric/milestones{/number}",
            "notifications_url": "https://api.github.com/repos/Samuel-Martineau/Potions-HUD-Fabric/notifications{?since,all,participating}",
            "labels_url": "https://api.github.com/repos/Samuel-Martineau/Potions-HUD-Fabric/labels{/name}",
            "releases_url": "https://api.github.com/repos/Samuel-Martineau/Potions-HUD-Fabric/releases{/id}",
            "deployments_url": "https://api.github.com/repos/Samuel-Martineau/Potions-HUD-Fabric/deployments",
            "created_at": "2020-07-18T21:30:46Z",
            "updated_at": "2020-07-20T13:57:11Z",
            "pushed_at": "2020-07-20T18:34:24Z",
            "git_url": "git://github.com/Samuel-Martineau/Potions-HUD-Fabric.git",
            "ssh_url": "git@github.com:Samuel-Martineau/Potions-HUD-Fabric.git",
            "clone_url": "https://github.com/Samuel-Martineau/Potions-HUD-Fabric.git",
            "svn_url": "https://github.com/Samuel-Martineau/Potions-HUD-Fabric",
            "homepage": "",
            "size": 3139,
            "stargazers_count": 1,
            "watchers_count": 1,
            "language": "Java",
            "has_issues": true,
            "has_projects": true,
            "has_downloads": true,
            "has_wiki": true,
            "has_pages": false,
            "forks_count": 1,
            "mirror_url": null,
            "archived": false,
            "disabled": false,
            "open_issues_count": 0,
            "license": {
              "key": "mit",
              "name": "MIT License",
              "spdx_id": "MIT",
              "url": "https://api.github.com/licenses/mit",
              "node_id": "MDc6TGljZW5zZTEz"
            },
            "forks": 1,
            "open_issues": 0,
            "watchers": 1,
            "default_branch": "master"
          }
        },
        "_links": {
          "self": {
            "href": "https://api.github.com/repos/Samuel-Martineau/Potions-HUD-Fabric/pulls/1"
          },
          "html": {
            "href": "https://github.com/Samuel-Martineau/Potions-HUD-Fabric/pull/1"
          },
          "issue": {
            "href": "https://api.github.com/repos/Samuel-Martineau/Potions-HUD-Fabric/issues/1"
          },
          "comments": {
            "href": "https://api.github.com/repos/Samuel-Martineau/Potions-HUD-Fabric/issues/1/comments"
          },
          "review_comments": {
            "href": "https://api.github.com/repos/Samuel-Martineau/Potions-HUD-Fabric/pulls/1/comments"
          },
          "review_comment": {
            "href": "https://api.github.com/repos/Samuel-Martineau/Potions-HUD-Fabric/pulls/comments{/number}"
          },
          "commits": {
            "href": "https://api.github.com/repos/Samuel-Martineau/Potions-HUD-Fabric/pulls/1/commits"
          },
          "statuses": {
            "href": "https://api.github.com/repos/Samuel-Martineau/Potions-HUD-Fabric/statuses/32bdf4c9411a9ed8034381a1c53c560fdd87fd2b"
          }
        },
        "author_association": "NONE",
        "active_lock_reason": null,
        "merged": true,
        "mergeable": null,
        "rebaseable": null,
        "mergeable_state": "unknown",
        "merged_by": {
          "login": "Samuel-Martineau",
          "id": 44237969,
          "node_id": "MDQ6VXNlcjQ0MjM3OTY5",
          "avatar_url": "https://avatars3.githubusercontent.com/u/44237969?v=4",
          "gravatar_id": "",
          "url": "https://api.github.com/users/Samuel-Martineau",
          "html_url": "https://github.com/Samuel-Martineau",
          "followers_url": "https://api.github.com/users/Samuel-Martineau/followers",
          "following_url": "https://api.github.com/users/Samuel-Martineau/following{/other_user}",
          "gists_url": "https://api.github.com/users/Samuel-Martineau/gists{/gist_id}",
          "starred_url": "https://api.github.com/users/Samuel-Martineau/starred{/owner}{/repo}",
          "subscriptions_url": "https://api.github.com/users/Samuel-Martineau/subscriptions",
          "organizations_url": "https://api.github.com/users/Samuel-Martineau/orgs",
          "repos_url": "https://api.github.com/users/Samuel-Martineau/repos",
          "events_url": "https://api.github.com/users/Samuel-Martineau/events{/privacy}",
          "received_events_url": "https://api.github.com/users/Samuel-Martineau/received_events",
          "type": "User",
          "site_admin": false
        },
        "comments": 0,
        "review_comments": 0,
        "maintainer_can_modify": false,
        "commits": 2,
        "additions": 1,
        "deletions": 1,
        "changed_files": 4
      }
    },
    "public": true,
    "created_at": "2020-07-20T18:34:25Z"
  },
  {
    "id": "12963308040",
    "type": "PushEvent",
    "actor": {
      "id": 44237969,
      "login": "Samuel-Martineau",
      "display_login": "Samuel-Martineau",
      "gravatar_id": "",
      "url": "https://api.github.com/users/Samuel-Martineau",
      "avatar_url": "https://avatars.githubusercontent.com/u/44237969?"
    },
    "repo": {
      "id": 280742722,
      "name": "Samuel-Martineau/Potions-HUD-Fabric",
      "url": "https://api.github.com/repos/Samuel-Martineau/Potions-HUD-Fabric"
    },
    "payload": {
      "push_id": 5403995921,
      "size": 3,
      "distinct_size": 3,
      "ref": "refs/heads/master",
      "head": "c848859fde8dbfd5da4c67c68232fb9063c3f83c",
      "before": "cffa02dcc0fa9d3f9703abaee7d24fe11f63a573",
      "commits": [
        {
          "sha": "02fb1436865e80647e64b3401a9488a4a18944fd",
          "author": {
            "email": "cvdkhoa@gmail.com",
            "name": "Vu Dang Khoa Chiem"
          },
          "message": "logo change",
          "distinct": true,
          "url": "https://api.github.com/repos/Samuel-Martineau/Potions-HUD-Fabric/commits/02fb1436865e80647e64b3401a9488a4a18944fd"
        },
        {
          "sha": "32bdf4c9411a9ed8034381a1c53c560fdd87fd2b",
          "author": {
            "email": "cvdkhoa@gmail.com",
            "name": "Vu Dang Khoa Chiem"
          },
          "message": "logo change",
          "distinct": true,
          "url": "https://api.github.com/repos/Samuel-Martineau/Potions-HUD-Fabric/commits/32bdf4c9411a9ed8034381a1c53c560fdd87fd2b"
        },
        {
          "sha": "c848859fde8dbfd5da4c67c68232fb9063c3f83c",
          "author": {
            "email": "samumartineau@gmail.com",
            "name": "Samuel Martineau"
          },
          "message": "Merge pull request #1 from Doudou8/master\n\nLogo change",
          "distinct": true,
          "url": "https://api.github.com/repos/Samuel-Martineau/Potions-HUD-Fabric/commits/c848859fde8dbfd5da4c67c68232fb9063c3f83c"
        }
      ]
    },
    "public": true,
    "created_at": "2020-07-20T18:34:26Z"
  },
  {
    "id": "12962544039",
    "type": "WatchEvent",
    "actor": {
      "id": 44237969,
      "login": "Samuel-Martineau",
      "display_login": "Samuel-Martineau",
      "gravatar_id": "",
      "url": "https://api.github.com/users/Samuel-Martineau",
      "avatar_url": "https://avatars.githubusercontent.com/u/44237969?"
    },
    "repo": {
      "id": 278422605,
      "name": "sindresorhus/sindresorhus",
      "url": "https://api.github.com/repos/sindresorhus/sindresorhus"
    },
    "payload": {
      "action": "started"
    },
    "public": true,
    "created_at": "2020-07-20T17:19:32Z"
  },
  {
    "id": "12962535761",
    "type": "WatchEvent",
    "actor": {
      "id": 44237969,
      "login": "Samuel-Martineau",
      "display_login": "Samuel-Martineau",
      "gravatar_id": "",
      "url": "https://api.github.com/users/Samuel-Martineau",
      "avatar_url": "https://avatars.githubusercontent.com/u/44237969?"
    },
    "repo": {
      "id": 280769136,
      "name": "Doudou8/Doudou8",
      "url": "https://api.github.com/repos/Doudou8/Doudou8"
    },
    "payload": {
      "action": "started"
    },
    "public": true,
    "created_at": "2020-07-20T17:18:47Z"
  },
  {
    "id": "12961572181",
    "type": "PushEvent",
    "actor": {
      "id": 44237969,
      "login": "Samuel-Martineau",
      "display_login": "Samuel-Martineau",
      "gravatar_id": "",
      "url": "https://api.github.com/users/Samuel-Martineau",
      "avatar_url": "https://avatars.githubusercontent.com/u/44237969?"
    },
    "repo": {
      "id": 199178623,
      "name": "Samuel-Martineau/Password-Generator",
      "url": "https://api.github.com/repos/Samuel-Martineau/Password-Generator"
    },
    "payload": {
      "push_id": 5403145997,
      "size": 2,
      "distinct_size": 1,
      "ref": "refs/heads/master",
      "head": "f5ff85fb3626e4c4368388a1b27a67082aaaadb3",
      "before": "0401f945c8c5f7249e52e605c0ad8269ba286ffe",
      "commits": [
        {
          "sha": "68995aac246aff9ce1075be12110b8cfca190cfd",
          "author": {
            "email": "49699333+dependabot[bot]@users.noreply.github.com",
            "name": "dependabot[bot]"
          },
          "message": "Bump lodash from 4.17.15 to 4.17.19\n\nBumps [lodash](https://github.com/lodash/lodash) from 4.17.15 to 4.17.19.\n- [Release notes](https://github.com/lodash/lodash/releases)\n- [Commits](https://github.com/lodash/lodash/compare/4.17.15...4.17.19)\n\nSigned-off-by: dependabot[bot] <support@github.com>",
          "distinct": false,
          "url": "https://api.github.com/repos/Samuel-Martineau/Password-Generator/commits/68995aac246aff9ce1075be12110b8cfca190cfd"
        },
        {
          "sha": "f5ff85fb3626e4c4368388a1b27a67082aaaadb3",
          "author": {
            "email": "samumartineau@gmail.com",
            "name": "Samuel Martineau"
          },
          "message": "Merge pull request #6 from Samuel-Martineau/dependabot/npm_and_yarn/lodash-4.17.19\n\nBump lodash from 4.17.15 to 4.17.19",
          "distinct": true,
          "url": "https://api.github.com/repos/Samuel-Martineau/Password-Generator/commits/f5ff85fb3626e4c4368388a1b27a67082aaaadb3"
        }
      ]
    },
    "public": true,
    "created_at": "2020-07-20T15:51:32Z"
  },
  {
    "id": "12961572787",
    "type": "DeleteEvent",
    "actor": {
      "id": 44237969,
      "login": "Samuel-Martineau",
      "display_login": "Samuel-Martineau",
      "gravatar_id": "",
      "url": "https://api.github.com/users/Samuel-Martineau",
      "avatar_url": "https://avatars.githubusercontent.com/u/44237969?"
    },
    "repo": {
      "id": 199178623,
      "name": "Samuel-Martineau/Password-Generator",
      "url": "https://api.github.com/repos/Samuel-Martineau/Password-Generator"
    },
    "payload": {
      "ref": "dependabot/npm_and_yarn/lodash-4.17.19",
      "ref_type": "branch",
      "pusher_type": "user"
    },
    "public": true,
    "created_at": "2020-07-20T15:51:35Z"
  },
  {
    "id": "12961572033",
    "type": "PullRequestEvent",
    "actor": {
      "id": 44237969,
      "login": "Samuel-Martineau",
      "display_login": "Samuel-Martineau",
      "gravatar_id": "",
      "url": "https://api.github.com/users/Samuel-Martineau",
      "avatar_url": "https://avatars.githubusercontent.com/u/44237969?"
    },
    "repo": {
      "id": 199178623,
      "name": "Samuel-Martineau/Password-Generator",
      "url": "https://api.github.com/repos/Samuel-Martineau/Password-Generator"
    },
    "payload": {
      "action": "closed",
      "number": 6,
      "pull_request": {
        "url": "https://api.github.com/repos/Samuel-Martineau/Password-Generator/pulls/6",
        "id": 451455482,
        "node_id": "MDExOlB1bGxSZXF1ZXN0NDUxNDU1NDgy",
        "html_url": "https://github.com/Samuel-Martineau/Password-Generator/pull/6",
        "diff_url": "https://github.com/Samuel-Martineau/Password-Generator/pull/6.diff",
        "patch_url": "https://github.com/Samuel-Martineau/Password-Generator/pull/6.patch",
        "issue_url": "https://api.github.com/repos/Samuel-Martineau/Password-Generator/issues/6",
        "number": 6,
        "state": "closed",
        "locked": false,
        "title": "Bump lodash from 4.17.15 to 4.17.19",
        "user": {
          "login": "dependabot[bot]",
          "id": 49699333,
          "node_id": "MDM6Qm90NDk2OTkzMzM=",
          "avatar_url": "https://avatars0.githubusercontent.com/in/29110?v=4",
          "gravatar_id": "",
          "url": "https://api.github.com/users/dependabot%5Bbot%5D",
          "html_url": "https://github.com/apps/dependabot",
          "followers_url": "https://api.github.com/users/dependabot%5Bbot%5D/followers",
          "following_url": "https://api.github.com/users/dependabot%5Bbot%5D/following{/other_user}",
          "gists_url": "https://api.github.com/users/dependabot%5Bbot%5D/gists{/gist_id}",
          "starred_url": "https://api.github.com/users/dependabot%5Bbot%5D/starred{/owner}{/repo}",
          "subscriptions_url": "https://api.github.com/users/dependabot%5Bbot%5D/subscriptions",
          "organizations_url": "https://api.github.com/users/dependabot%5Bbot%5D/orgs",
          "repos_url": "https://api.github.com/users/dependabot%5Bbot%5D/repos",
          "events_url": "https://api.github.com/users/dependabot%5Bbot%5D/events{/privacy}",
          "received_events_url": "https://api.github.com/users/dependabot%5Bbot%5D/received_events",
          "type": "Bot",
          "site_admin": false
        },
        "body": "Bumps [lodash](https://github.com/lodash/lodash) from 4.17.15 to 4.17.19.\n<details>\n<summary>Release notes</summary>\n<p><em>Sourced from <a href=\"https://github.com/lodash/lodash/releases\">lodash's releases</a>.</em></p>\n<blockquote>\n<h2>4.17.16</h2>\n</blockquote>\n</details>\n<details>\n<summary>Commits</summary>\n<ul>\n<li><a href=\"https://github.com/lodash/lodash/commit/d7fbc52ee0466a6d248f047b5d5c3e6d1e099056\"><code>d7fbc52</code></a> Bump to v4.17.19</li>\n<li><a href=\"https://github.com/lodash/lodash/commit/2e1c0f22f425e9c013815b2cd7c2ebd51f49a8d6\"><code>2e1c0f2</code></a> Add npm-package</li>\n<li><a href=\"https://github.com/lodash/lodash/commit/1b6c282299f4e0271f932b466c67f0f822aa308e\"><code>1b6c282</code></a> Bump to v4.17.18</li>\n<li><a href=\"https://github.com/lodash/lodash/commit/a370ac81408de2da77a82b3c4b61a01a3b9c2fac\"><code>a370ac8</code></a> Bump to v4.17.17</li>\n<li><a href=\"https://github.com/lodash/lodash/commit/1144918f3578a84fcc4986da9b806e63a6175cbb\"><code>1144918</code></a> Rebuild lodash and docs</li>\n<li><a href=\"https://github.com/lodash/lodash/commit/3a3b0fd339c2109563f7e8167dc95265ed82ef3e\"><code>3a3b0fd</code></a> Bump to v4.17.16</li>\n<li><a href=\"https://github.com/lodash/lodash/commit/c84fe82760fb2d3e03a63379b297a1cc1a2fce12\"><code>c84fe82</code></a> fix(zipObjectDeep): prototype pollution (<a href=\"https://github-redirect.dependabot.com/lodash/lodash/issues/4759\">#4759</a>)</li>\n<li><a href=\"https://github.com/lodash/lodash/commit/e7b28ea6cb17b4ca021e7c9d66218c8c89782f32\"><code>e7b28ea</code></a> Sanitize sourceURL so it cannot affect evaled code (<a href=\"https://github-redirect.dependabot.com/lodash/lodash/issues/4518\">#4518</a>)</li>\n<li><a href=\"https://github.com/lodash/lodash/commit/0cec225778d4ac26c2bac95031ecc92a94f08bbb\"><code>0cec225</code></a> Fix lodash.isEqual for circular references (<a href=\"https://github-redirect.dependabot.com/lodash/lodash/issues/4320\">#4320</a>) (<a href=\"https://github-redirect.dependabot.com/lodash/lodash/issues/4515\">#4515</a>)</li>\n<li><a href=\"https://github.com/lodash/lodash/commit/94c3a8133cb4fcdb50db72b4fd14dd884b195cd5\"><code>94c3a81</code></a> Document matches* shorthands for over* methods (<a href=\"https://github-redirect.dependabot.com/lodash/lodash/issues/4510\">#4510</a>) (<a href=\"https://github-redirect.dependabot.com/lodash/lodash/issues/4514\">#4514</a>)</li>\n<li>Additional commits viewable in <a href=\"https://github.com/lodash/lodash/compare/4.17.15...4.17.19\">compare view</a></li>\n</ul>\n</details>\n<details>\n<summary>Maintainer changes</summary>\n<p>This version was pushed to npm by <a href=\"https://www.npmjs.com/~mathias\">mathias</a>, a new releaser for lodash since your current version.</p>\n</details>\n<br />\n\n\n[![Dependabot compatibility score](https://dependabot-badges.githubapp.com/badges/compatibility_score?dependency-name=lodash&package-manager=npm_and_yarn&previous-version=4.17.15&new-version=4.17.19)](https://help.github.com/articles/configuring-automated-security-fixes)\n\nDependabot will resolve any conflicts with this PR as long as you don't alter it yourself. You can also trigger a rebase manually by commenting `@dependabot rebase`.\n\n[//]: # (dependabot-automerge-start)\n[//]: # (dependabot-automerge-end)\n\n---\n\n<details>\n<summary>Dependabot commands and options</summary>\n<br />\n\nYou can trigger Dependabot actions by commenting on this PR:\n- `@dependabot rebase` will rebase this PR\n- `@dependabot recreate` will recreate this PR, overwriting any edits that have been made to it\n- `@dependabot merge` will merge this PR after your CI passes on it\n- `@dependabot squash and merge` will squash and merge this PR after your CI passes on it\n- `@dependabot cancel merge` will cancel a previously requested merge and block automerging\n- `@dependabot reopen` will reopen this PR if it is closed\n- `@dependabot close` will close this PR and stop Dependabot recreating it. You can achieve the same result by closing it manually\n- `@dependabot ignore this major version` will close this PR and stop Dependabot creating any more for this major version (unless you reopen the PR or upgrade to it yourself)\n- `@dependabot ignore this minor version` will close this PR and stop Dependabot creating any more for this minor version (unless you reopen the PR or upgrade to it yourself)\n- `@dependabot ignore this dependency` will close this PR and stop Dependabot creating any more for this dependency (unless you reopen the PR or upgrade to it yourself)\n- `@dependabot use these labels` will set the current labels as the default for future PRs for this repo and language\n- `@dependabot use these reviewers` will set the current reviewers as the default for future PRs for this repo and language\n- `@dependabot use these assignees` will set the current assignees as the default for future PRs for this repo and language\n- `@dependabot use this milestone` will set the current milestone as the default for future PRs for this repo and language\n\nYou can disable automated security fix PRs for this repo from the [Security Alerts page](https://github.com/Samuel-Martineau/Password-Generator/network/alerts).\n\n</details>",
        "created_at": "2020-07-17T20:53:04Z",
        "updated_at": "2020-07-20T15:51:30Z",
        "closed_at": "2020-07-20T15:51:30Z",
        "merged_at": "2020-07-20T15:51:30Z",
        "merge_commit_sha": "f5ff85fb3626e4c4368388a1b27a67082aaaadb3",
        "assignee": null,
        "assignees": [],
        "requested_reviewers": [],
        "requested_teams": [],
        "labels": [
          {
            "id": 1761356466,
            "node_id": "MDU6TGFiZWwxNzYxMzU2NDY2",
            "url": "https://api.github.com/repos/Samuel-Martineau/Password-Generator/labels/dependencies",
            "name": "dependencies",
            "color": "0366d6",
            "default": false,
            "description": "Pull requests that update a dependency file"
          }
        ],
        "milestone": null,
        "draft": false,
        "commits_url": "https://api.github.com/repos/Samuel-Martineau/Password-Generator/pulls/6/commits",
        "review_comments_url": "https://api.github.com/repos/Samuel-Martineau/Password-Generator/pulls/6/comments",
        "review_comment_url": "https://api.github.com/repos/Samuel-Martineau/Password-Generator/pulls/comments{/number}",
        "comments_url": "https://api.github.com/repos/Samuel-Martineau/Password-Generator/issues/6/comments",
        "statuses_url": "https://api.github.com/repos/Samuel-Martineau/Password-Generator/statuses/68995aac246aff9ce1075be12110b8cfca190cfd",
        "head": {
          "label": "Samuel-Martineau:dependabot/npm_and_yarn/lodash-4.17.19",
          "ref": "dependabot/npm_and_yarn/lodash-4.17.19",
          "sha": "68995aac246aff9ce1075be12110b8cfca190cfd",
          "user": {
            "login": "Samuel-Martineau",
            "id": 44237969,
            "node_id": "MDQ6VXNlcjQ0MjM3OTY5",
            "avatar_url": "https://avatars3.githubusercontent.com/u/44237969?v=4",
            "gravatar_id": "",
            "url": "https://api.github.com/users/Samuel-Martineau",
            "html_url": "https://github.com/Samuel-Martineau",
            "followers_url": "https://api.github.com/users/Samuel-Martineau/followers",
            "following_url": "https://api.github.com/users/Samuel-Martineau/following{/other_user}",
            "gists_url": "https://api.github.com/users/Samuel-Martineau/gists{/gist_id}",
            "starred_url": "https://api.github.com/users/Samuel-Martineau/starred{/owner}{/repo}",
            "subscriptions_url": "https://api.github.com/users/Samuel-Martineau/subscriptions",
            "organizations_url": "https://api.github.com/users/Samuel-Martineau/orgs",
            "repos_url": "https://api.github.com/users/Samuel-Martineau/repos",
            "events_url": "https://api.github.com/users/Samuel-Martineau/events{/privacy}",
            "received_events_url": "https://api.github.com/users/Samuel-Martineau/received_events",
            "type": "User",
            "site_admin": false
          },
          "repo": {
            "id": 199178623,
            "node_id": "MDEwOlJlcG9zaXRvcnkxOTkxNzg2MjM=",
            "name": "Password-Generator",
            "full_name": "Samuel-Martineau/Password-Generator",
            "private": false,
            "owner": {
              "login": "Samuel-Martineau",
              "id": 44237969,
              "node_id": "MDQ6VXNlcjQ0MjM3OTY5",
              "avatar_url": "https://avatars3.githubusercontent.com/u/44237969?v=4",
              "gravatar_id": "",
              "url": "https://api.github.com/users/Samuel-Martineau",
              "html_url": "https://github.com/Samuel-Martineau",
              "followers_url": "https://api.github.com/users/Samuel-Martineau/followers",
              "following_url": "https://api.github.com/users/Samuel-Martineau/following{/other_user}",
              "gists_url": "https://api.github.com/users/Samuel-Martineau/gists{/gist_id}",
              "starred_url": "https://api.github.com/users/Samuel-Martineau/starred{/owner}{/repo}",
              "subscriptions_url": "https://api.github.com/users/Samuel-Martineau/subscriptions",
              "organizations_url": "https://api.github.com/users/Samuel-Martineau/orgs",
              "repos_url": "https://api.github.com/users/Samuel-Martineau/repos",
              "events_url": "https://api.github.com/users/Samuel-Martineau/events{/privacy}",
              "received_events_url": "https://api.github.com/users/Samuel-Martineau/received_events",
              "type": "User",
              "site_admin": false
            },
            "html_url": "https://github.com/Samuel-Martineau/Password-Generator",
            "description": "A basic password generator built with Angular and Electron",
            "fork": false,
            "url": "https://api.github.com/repos/Samuel-Martineau/Password-Generator",
            "forks_url": "https://api.github.com/repos/Samuel-Martineau/Password-Generator/forks",
            "keys_url": "https://api.github.com/repos/Samuel-Martineau/Password-Generator/keys{/key_id}",
            "collaborators_url": "https://api.github.com/repos/Samuel-Martineau/Password-Generator/collaborators{/collaborator}",
            "teams_url": "https://api.github.com/repos/Samuel-Martineau/Password-Generator/teams",
            "hooks_url": "https://api.github.com/repos/Samuel-Martineau/Password-Generator/hooks",
            "issue_events_url": "https://api.github.com/repos/Samuel-Martineau/Password-Generator/issues/events{/number}",
            "events_url": "https://api.github.com/repos/Samuel-Martineau/Password-Generator/events",
            "assignees_url": "https://api.github.com/repos/Samuel-Martineau/Password-Generator/assignees{/user}",
            "branches_url": "https://api.github.com/repos/Samuel-Martineau/Password-Generator/branches{/branch}",
            "tags_url": "https://api.github.com/repos/Samuel-Martineau/Password-Generator/tags",
            "blobs_url": "https://api.github.com/repos/Samuel-Martineau/Password-Generator/git/blobs{/sha}",
            "git_tags_url": "https://api.github.com/repos/Samuel-Martineau/Password-Generator/git/tags{/sha}",
            "git_refs_url": "https://api.github.com/repos/Samuel-Martineau/Password-Generator/git/refs{/sha}",
            "trees_url": "https://api.github.com/repos/Samuel-Martineau/Password-Generator/git/trees{/sha}",
            "statuses_url": "https://api.github.com/repos/Samuel-Martineau/Password-Generator/statuses/{sha}",
            "languages_url": "https://api.github.com/repos/Samuel-Martineau/Password-Generator/languages",
            "stargazers_url": "https://api.github.com/repos/Samuel-Martineau/Password-Generator/stargazers",
            "contributors_url": "https://api.github.com/repos/Samuel-Martineau/Password-Generator/contributors",
            "subscribers_url": "https://api.github.com/repos/Samuel-Martineau/Password-Generator/subscribers",
            "subscription_url": "https://api.github.com/repos/Samuel-Martineau/Password-Generator/subscription",
            "commits_url": "https://api.github.com/repos/Samuel-Martineau/Password-Generator/commits{/sha}",
            "git_commits_url": "https://api.github.com/repos/Samuel-Martineau/Password-Generator/git/commits{/sha}",
            "comments_url": "https://api.github.com/repos/Samuel-Martineau/Password-Generator/comments{/number}",
            "issue_comment_url": "https://api.github.com/repos/Samuel-Martineau/Password-Generator/issues/comments{/number}",
            "contents_url": "https://api.github.com/repos/Samuel-Martineau/Password-Generator/contents/{+path}",
            "compare_url": "https://api.github.com/repos/Samuel-Martineau/Password-Generator/compare/{base}...{head}",
            "merges_url": "https://api.github.com/repos/Samuel-Martineau/Password-Generator/merges",
            "archive_url": "https://api.github.com/repos/Samuel-Martineau/Password-Generator/{archive_format}{/ref}",
            "downloads_url": "https://api.github.com/repos/Samuel-Martineau/Password-Generator/downloads",
            "issues_url": "https://api.github.com/repos/Samuel-Martineau/Password-Generator/issues{/number}",
            "pulls_url": "https://api.github.com/repos/Samuel-Martineau/Password-Generator/pulls{/number}",
            "milestones_url": "https://api.github.com/repos/Samuel-Martineau/Password-Generator/milestones{/number}",
            "notifications_url": "https://api.github.com/repos/Samuel-Martineau/Password-Generator/notifications{?since,all,participating}",
            "labels_url": "https://api.github.com/repos/Samuel-Martineau/Password-Generator/labels{/name}",
            "releases_url": "https://api.github.com/repos/Samuel-Martineau/Password-Generator/releases{/id}",
            "deployments_url": "https://api.github.com/repos/Samuel-Martineau/Password-Generator/deployments",
            "created_at": "2019-07-27T14:58:28Z",
            "updated_at": "2020-07-07T18:20:35Z",
            "pushed_at": "2020-07-20T15:51:30Z",
            "git_url": "git://github.com/Samuel-Martineau/Password-Generator.git",
            "ssh_url": "git@github.com:Samuel-Martineau/Password-Generator.git",
            "clone_url": "https://github.com/Samuel-Martineau/Password-Generator.git",
            "svn_url": "https://github.com/Samuel-Martineau/Password-Generator",
            "homepage": "https://smartineau.me/projets/password-generator",
            "size": 1568,
            "stargazers_count": 0,
            "watchers_count": 0,
            "language": "TypeScript",
            "has_issues": true,
            "has_projects": true,
            "has_downloads": true,
            "has_wiki": true,
            "has_pages": false,
            "forks_count": 0,
            "mirror_url": null,
            "archived": false,
            "disabled": false,
            "open_issues_count": 0,
            "license": {
              "key": "mit",
              "name": "MIT License",
              "spdx_id": "MIT",
              "url": "https://api.github.com/licenses/mit",
              "node_id": "MDc6TGljZW5zZTEz"
            },
            "forks": 0,
            "open_issues": 0,
            "watchers": 0,
            "default_branch": "master"
          }
        },
        "base": {
          "label": "Samuel-Martineau:master",
          "ref": "master",
          "sha": "0401f945c8c5f7249e52e605c0ad8269ba286ffe",
          "user": {
            "login": "Samuel-Martineau",
            "id": 44237969,
            "node_id": "MDQ6VXNlcjQ0MjM3OTY5",
            "avatar_url": "https://avatars3.githubusercontent.com/u/44237969?v=4",
            "gravatar_id": "",
            "url": "https://api.github.com/users/Samuel-Martineau",
            "html_url": "https://github.com/Samuel-Martineau",
            "followers_url": "https://api.github.com/users/Samuel-Martineau/followers",
            "following_url": "https://api.github.com/users/Samuel-Martineau/following{/other_user}",
            "gists_url": "https://api.github.com/users/Samuel-Martineau/gists{/gist_id}",
            "starred_url": "https://api.github.com/users/Samuel-Martineau/starred{/owner}{/repo}",
            "subscriptions_url": "https://api.github.com/users/Samuel-Martineau/subscriptions",
            "organizations_url": "https://api.github.com/users/Samuel-Martineau/orgs",
            "repos_url": "https://api.github.com/users/Samuel-Martineau/repos",
            "events_url": "https://api.github.com/users/Samuel-Martineau/events{/privacy}",
            "received_events_url": "https://api.github.com/users/Samuel-Martineau/received_events",
            "type": "User",
            "site_admin": false
          },
          "repo": {
            "id": 199178623,
            "node_id": "MDEwOlJlcG9zaXRvcnkxOTkxNzg2MjM=",
            "name": "Password-Generator",
            "full_name": "Samuel-Martineau/Password-Generator",
            "private": false,
            "owner": {
              "login": "Samuel-Martineau",
              "id": 44237969,
              "node_id": "MDQ6VXNlcjQ0MjM3OTY5",
              "avatar_url": "https://avatars3.githubusercontent.com/u/44237969?v=4",
              "gravatar_id": "",
              "url": "https://api.github.com/users/Samuel-Martineau",
              "html_url": "https://github.com/Samuel-Martineau",
              "followers_url": "https://api.github.com/users/Samuel-Martineau/followers",
              "following_url": "https://api.github.com/users/Samuel-Martineau/following{/other_user}",
              "gists_url": "https://api.github.com/users/Samuel-Martineau/gists{/gist_id}",
              "starred_url": "https://api.github.com/users/Samuel-Martineau/starred{/owner}{/repo}",
              "subscriptions_url": "https://api.github.com/users/Samuel-Martineau/subscriptions",
              "organizations_url": "https://api.github.com/users/Samuel-Martineau/orgs",
              "repos_url": "https://api.github.com/users/Samuel-Martineau/repos",
              "events_url": "https://api.github.com/users/Samuel-Martineau/events{/privacy}",
              "received_events_url": "https://api.github.com/users/Samuel-Martineau/received_events",
              "type": "User",
              "site_admin": false
            },
            "html_url": "https://github.com/Samuel-Martineau/Password-Generator",
            "description": "A basic password generator built with Angular and Electron",
            "fork": false,
            "url": "https://api.github.com/repos/Samuel-Martineau/Password-Generator",
            "forks_url": "https://api.github.com/repos/Samuel-Martineau/Password-Generator/forks",
            "keys_url": "https://api.github.com/repos/Samuel-Martineau/Password-Generator/keys{/key_id}",
            "collaborators_url": "https://api.github.com/repos/Samuel-Martineau/Password-Generator/collaborators{/collaborator}",
            "teams_url": "https://api.github.com/repos/Samuel-Martineau/Password-Generator/teams",
            "hooks_url": "https://api.github.com/repos/Samuel-Martineau/Password-Generator/hooks",
            "issue_events_url": "https://api.github.com/repos/Samuel-Martineau/Password-Generator/issues/events{/number}",
            "events_url": "https://api.github.com/repos/Samuel-Martineau/Password-Generator/events",
            "assignees_url": "https://api.github.com/repos/Samuel-Martineau/Password-Generator/assignees{/user}",
            "branches_url": "https://api.github.com/repos/Samuel-Martineau/Password-Generator/branches{/branch}",
            "tags_url": "https://api.github.com/repos/Samuel-Martineau/Password-Generator/tags",
            "blobs_url": "https://api.github.com/repos/Samuel-Martineau/Password-Generator/git/blobs{/sha}",
            "git_tags_url": "https://api.github.com/repos/Samuel-Martineau/Password-Generator/git/tags{/sha}",
            "git_refs_url": "https://api.github.com/repos/Samuel-Martineau/Password-Generator/git/refs{/sha}",
            "trees_url": "https://api.github.com/repos/Samuel-Martineau/Password-Generator/git/trees{/sha}",
            "statuses_url": "https://api.github.com/repos/Samuel-Martineau/Password-Generator/statuses/{sha}",
            "languages_url": "https://api.github.com/repos/Samuel-Martineau/Password-Generator/languages",
            "stargazers_url": "https://api.github.com/repos/Samuel-Martineau/Password-Generator/stargazers",
            "contributors_url": "https://api.github.com/repos/Samuel-Martineau/Password-Generator/contributors",
            "subscribers_url": "https://api.github.com/repos/Samuel-Martineau/Password-Generator/subscribers",
            "subscription_url": "https://api.github.com/repos/Samuel-Martineau/Password-Generator/subscription",
            "commits_url": "https://api.github.com/repos/Samuel-Martineau/Password-Generator/commits{/sha}",
            "git_commits_url": "https://api.github.com/repos/Samuel-Martineau/Password-Generator/git/commits{/sha}",
            "comments_url": "https://api.github.com/repos/Samuel-Martineau/Password-Generator/comments{/number}",
            "issue_comment_url": "https://api.github.com/repos/Samuel-Martineau/Password-Generator/issues/comments{/number}",
            "contents_url": "https://api.github.com/repos/Samuel-Martineau/Password-Generator/contents/{+path}",
            "compare_url": "https://api.github.com/repos/Samuel-Martineau/Password-Generator/compare/{base}...{head}",
            "merges_url": "https://api.github.com/repos/Samuel-Martineau/Password-Generator/merges",
            "archive_url": "https://api.github.com/repos/Samuel-Martineau/Password-Generator/{archive_format}{/ref}",
            "downloads_url": "https://api.github.com/repos/Samuel-Martineau/Password-Generator/downloads",
            "issues_url": "https://api.github.com/repos/Samuel-Martineau/Password-Generator/issues{/number}",
            "pulls_url": "https://api.github.com/repos/Samuel-Martineau/Password-Generator/pulls{/number}",
            "milestones_url": "https://api.github.com/repos/Samuel-Martineau/Password-Generator/milestones{/number}",
            "notifications_url": "https://api.github.com/repos/Samuel-Martineau/Password-Generator/notifications{?since,all,participating}",
            "labels_url": "https://api.github.com/repos/Samuel-Martineau/Password-Generator/labels{/name}",
            "releases_url": "https://api.github.com/repos/Samuel-Martineau/Password-Generator/releases{/id}",
            "deployments_url": "https://api.github.com/repos/Samuel-Martineau/Password-Generator/deployments",
            "created_at": "2019-07-27T14:58:28Z",
            "updated_at": "2020-07-07T18:20:35Z",
            "pushed_at": "2020-07-20T15:51:30Z",
            "git_url": "git://github.com/Samuel-Martineau/Password-Generator.git",
            "ssh_url": "git@github.com:Samuel-Martineau/Password-Generator.git",
            "clone_url": "https://github.com/Samuel-Martineau/Password-Generator.git",
            "svn_url": "https://github.com/Samuel-Martineau/Password-Generator",
            "homepage": "https://smartineau.me/projets/password-generator",
            "size": 1568,
            "stargazers_count": 0,
            "watchers_count": 0,
            "language": "TypeScript",
            "has_issues": true,
            "has_projects": true,
            "has_downloads": true,
            "has_wiki": true,
            "has_pages": false,
            "forks_count": 0,
            "mirror_url": null,
            "archived": false,
            "disabled": false,
            "open_issues_count": 0,
            "license": {
              "key": "mit",
              "name": "MIT License",
              "spdx_id": "MIT",
              "url": "https://api.github.com/licenses/mit",
              "node_id": "MDc6TGljZW5zZTEz"
            },
            "forks": 0,
            "open_issues": 0,
            "watchers": 0,
            "default_branch": "master"
          }
        },
        "_links": {
          "self": {
            "href": "https://api.github.com/repos/Samuel-Martineau/Password-Generator/pulls/6"
          },
          "html": {
            "href": "https://github.com/Samuel-Martineau/Password-Generator/pull/6"
          },
          "issue": {
            "href": "https://api.github.com/repos/Samuel-Martineau/Password-Generator/issues/6"
          },
          "comments": {
            "href": "https://api.github.com/repos/Samuel-Martineau/Password-Generator/issues/6/comments"
          },
          "review_comments": {
            "href": "https://api.github.com/repos/Samuel-Martineau/Password-Generator/pulls/6/comments"
          },
          "review_comment": {
            "href": "https://api.github.com/repos/Samuel-Martineau/Password-Generator/pulls/comments{/number}"
          },
          "commits": {
            "href": "https://api.github.com/repos/Samuel-Martineau/Password-Generator/pulls/6/commits"
          },
          "statuses": {
            "href": "https://api.github.com/repos/Samuel-Martineau/Password-Generator/statuses/68995aac246aff9ce1075be12110b8cfca190cfd"
          }
        },
        "author_association": "CONTRIBUTOR",
        "active_lock_reason": null,
        "merged": true,
        "mergeable": null,
        "rebaseable": null,
        "mergeable_state": "unknown",
        "merged_by": {
          "login": "Samuel-Martineau",
          "id": 44237969,
          "node_id": "MDQ6VXNlcjQ0MjM3OTY5",
          "avatar_url": "https://avatars3.githubusercontent.com/u/44237969?v=4",
          "gravatar_id": "",
          "url": "https://api.github.com/users/Samuel-Martineau",
          "html_url": "https://github.com/Samuel-Martineau",
          "followers_url": "https://api.github.com/users/Samuel-Martineau/followers",
          "following_url": "https://api.github.com/users/Samuel-Martineau/following{/other_user}",
          "gists_url": "https://api.github.com/users/Samuel-Martineau/gists{/gist_id}",
          "starred_url": "https://api.github.com/users/Samuel-Martineau/starred{/owner}{/repo}",
          "subscriptions_url": "https://api.github.com/users/Samuel-Martineau/subscriptions",
          "organizations_url": "https://api.github.com/users/Samuel-Martineau/orgs",
          "repos_url": "https://api.github.com/users/Samuel-Martineau/repos",
          "events_url": "https://api.github.com/users/Samuel-Martineau/events{/privacy}",
          "received_events_url": "https://api.github.com/users/Samuel-Martineau/received_events",
          "type": "User",
          "site_admin": false
        },
        "comments": 0,
        "review_comments": 0,
        "maintainer_can_modify": false,
        "commits": 1,
        "additions": 3,
        "deletions": 3,
        "changed_files": 1
      }
    },
    "public": true,
    "created_at": "2020-07-20T15:51:31Z"
  },
  {
    "id": "12961425199",
    "type": "PushEvent",
    "actor": {
      "id": 44237969,
      "login": "Samuel-Martineau",
      "display_login": "Samuel-Martineau",
      "gravatar_id": "",
      "url": "https://api.github.com/users/Samuel-Martineau",
      "avatar_url": "https://avatars.githubusercontent.com/u/44237969?"
    },
    "repo": {
      "id": 228497599,
      "name": "Samuel-Martineau/Create-Custom-Command",
      "url": "https://api.github.com/repos/Samuel-Martineau/Create-Custom-Command"
    },
    "payload": {
      "push_id": 5403074015,
      "size": 1,
      "distinct_size": 1,
      "ref": "refs/heads/master",
      "head": "e12e3bca6ecb8c87bb2c7f00ea130ee3bc7e1d8a",
      "before": "7b9191acb7fee018f0f677ec573d3bf0b8f4956c",
      "commits": [
        {
          "sha": "e12e3bca6ecb8c87bb2c7f00ea130ee3bc7e1d8a",
          "author": {
            "email": "samumartineau@gmail.com",
            "name": "Samuel-Martineau"
          },
          "message": "Modification du README",
          "distinct": true,
          "url": "https://api.github.com/repos/Samuel-Martineau/Create-Custom-Command/commits/e12e3bca6ecb8c87bb2c7f00ea130ee3bc7e1d8a"
        }
      ]
    },
    "public": true,
    "created_at": "2020-07-20T15:39:22Z"
  },
  {
    "id": "12961392685",
    "type": "PushEvent",
    "actor": {
      "id": 44237969,
      "login": "Samuel-Martineau",
      "display_login": "Samuel-Martineau",
      "gravatar_id": "",
      "url": "https://api.github.com/users/Samuel-Martineau",
      "avatar_url": "https://avatars.githubusercontent.com/u/44237969?"
    },
    "repo": {
      "id": 195260491,
      "name": "Samuel-Martineau/RM-Comments-CLI",
      "url": "https://api.github.com/repos/Samuel-Martineau/RM-Comments-CLI"
    },
    "payload": {
      "push_id": 5403058000,
      "size": 1,
      "distinct_size": 1,
      "ref": "refs/heads/master",
      "head": "3efa676aa14d8cd0c3cb5f93acac11341810ee56",
      "before": "8f6265bf290281d3b011c8fa557e80511730811c",
      "commits": [
        {
          "sha": "3efa676aa14d8cd0c3cb5f93acac11341810ee56",
          "author": {
            "email": "samumartineau@gmail.com",
            "name": "Samuel-Martineau"
          },
          "message": "Update README.md",
          "distinct": true,
          "url": "https://api.github.com/repos/Samuel-Martineau/RM-Comments-CLI/commits/3efa676aa14d8cd0c3cb5f93acac11341810ee56"
        }
      ]
    },
    "public": true,
    "created_at": "2020-07-20T15:36:39Z"
  },
  {
    "id": "12961246188",
    "type": "DeleteEvent",
    "actor": {
      "id": 44237969,
      "login": "Samuel-Martineau",
      "display_login": "Samuel-Martineau",
      "gravatar_id": "",
      "url": "https://api.github.com/users/Samuel-Martineau",
      "avatar_url": "https://avatars.githubusercontent.com/u/44237969?"
    },
    "repo": {
      "id": 195260491,
      "name": "Samuel-Martineau/RM-Comments-CLI",
      "url": "https://api.github.com/repos/Samuel-Martineau/RM-Comments-CLI"
    },
    "payload": {
      "ref": "1.3.1",
      "ref_type": "tag",
      "pusher_type": "user"
    },
    "public": true,
    "created_at": "2020-07-20T15:24:40Z"
  },
  {
    "id": "12961223748",
    "type": "PushEvent",
    "actor": {
      "id": 44237969,
      "login": "Samuel-Martineau",
      "display_login": "Samuel-Martineau",
      "gravatar_id": "",
      "url": "https://api.github.com/users/Samuel-Martineau",
      "avatar_url": "https://avatars.githubusercontent.com/u/44237969?"
    },
    "repo": {
      "id": 195260491,
      "name": "Samuel-Martineau/RM-Comments-CLI",
      "url": "https://api.github.com/repos/Samuel-Martineau/RM-Comments-CLI"
    },
    "payload": {
      "push_id": 5402974891,
      "size": 1,
      "distinct_size": 1,
      "ref": "refs/heads/master",
      "head": "8f6265bf290281d3b011c8fa557e80511730811c",
      "before": "7dbeb2d8299510bda3a44c2e6b540018eb08157a",
      "commits": [
        {
          "sha": "8f6265bf290281d3b011c8fa557e80511730811c",
          "author": {
            "email": "samumartineau@gmail.com",
            "name": "Samuel-Martineau"
          },
          "message": "Small changes",
          "distinct": true,
          "url": "https://api.github.com/repos/Samuel-Martineau/RM-Comments-CLI/commits/8f6265bf290281d3b011c8fa557e80511730811c"
        }
      ]
    },
    "public": true,
    "created_at": "2020-07-20T15:22:52Z"
  },
  {
    "id": "12961210651",
    "type": "PushEvent",
    "actor": {
      "id": 44237969,
      "login": "Samuel-Martineau",
      "display_login": "Samuel-Martineau",
      "gravatar_id": "",
      "url": "https://api.github.com/users/Samuel-Martineau",
      "avatar_url": "https://avatars.githubusercontent.com/u/44237969?"
    },
    "repo": {
      "id": 195260491,
      "name": "Samuel-Martineau/RM-Comments-CLI",
      "url": "https://api.github.com/repos/Samuel-Martineau/RM-Comments-CLI"
    },
    "payload": {
      "push_id": 5402968310,
      "size": 2,
      "distinct_size": 2,
      "ref": "refs/heads/master",
      "head": "7dbeb2d8299510bda3a44c2e6b540018eb08157a",
      "before": "63ee0b77ecea29e752505d18ffe236dfa15eacb9",
      "commits": [
        {
          "sha": "809f1c7c7df175fab98ebdb331b15ee204c2e5cf",
          "author": {
            "email": "samumartineau@gmail.com",
            "name": "Samuel-Martineau"
          },
          "message": "Added CI (Github Actions)",
          "distinct": true,
          "url": "https://api.github.com/repos/Samuel-Martineau/RM-Comments-CLI/commits/809f1c7c7df175fab98ebdb331b15ee204c2e5cf"
        },
        {
          "sha": "7dbeb2d8299510bda3a44c2e6b540018eb08157a",
          "author": {
            "email": "samumartineau@gmail.com",
            "name": "Samuel-Martineau"
          },
          "message": "Merge branch 'master' of https://github.com/Samuel-Martineau/RM-Comments-CLI",
          "distinct": true,
          "url": "https://api.github.com/repos/Samuel-Martineau/RM-Comments-CLI/commits/7dbeb2d8299510bda3a44c2e6b540018eb08157a"
        }
      ]
    },
    "public": true,
    "created_at": "2020-07-20T15:21:49Z"
  },
  {
    "id": "12961175244",
    "type": "PushEvent",
    "actor": {
      "id": 44237969,
      "login": "Samuel-Martineau",
      "display_login": "Samuel-Martineau",
      "gravatar_id": "",
      "url": "https://api.github.com/users/Samuel-Martineau",
      "avatar_url": "https://avatars.githubusercontent.com/u/44237969?"
    },
    "repo": {
      "id": 279708123,
      "name": "Samuel-Martineau/Tetris-13kB-Game",
      "url": "https://api.github.com/repos/Samuel-Martineau/Tetris-13kB-Game"
    },
    "payload": {
      "push_id": 5402950604,
      "size": 1,
      "distinct_size": 1,
      "ref": "refs/heads/master",
      "head": "7576cb5f45d03918ecbcaa5b5986dd2975e215d5",
      "before": "6852c552f6721cac15ba493d598fa1157db13be4",
      "commits": [
        {
          "sha": "7576cb5f45d03918ecbcaa5b5986dd2975e215d5",
          "author": {
            "email": "samumartineau@gmail.com",
            "name": "Samuel Martineau"
          },
          "message": "Update main.yml",
          "distinct": true,
          "url": "https://api.github.com/repos/Samuel-Martineau/Tetris-13kB-Game/commits/7576cb5f45d03918ecbcaa5b5986dd2975e215d5"
        }
      ]
    },
    "public": true,
    "created_at": "2020-07-20T15:19:02Z"
  }
]